Java8JiaochengHuizong/README.md
Java8JiaochengHuizong/__init__.py
Java8JiaochengHuizong/__main__.py
Java8JiaochengHuizong/file.epub
Java8JiaochengHuizong/index.html
Java8JiaochengHuizong/css/__init__.py
Java8JiaochengHuizong/css/annotations.css
Java8JiaochengHuizong/css/main.css
Java8JiaochengHuizong/css/normalize.css
Java8JiaochengHuizong/css/popup.css
Java8JiaochengHuizong/font/__init__.py
Java8JiaochengHuizong/font/fontello.eot
Java8JiaochengHuizong/font/fontello.svg
Java8JiaochengHuizong/font/fontello.ttf
Java8JiaochengHuizong/font/fontello.woff
Java8JiaochengHuizong/img/__init__.py
Java8JiaochengHuizong/img/annotator-glyph-sprite.png
Java8JiaochengHuizong/img/annotator-icon-sprite.png
Java8JiaochengHuizong/img/apple-touch-icon.png
Java8JiaochengHuizong/img/cancelfullscreen.png
Java8JiaochengHuizong/img/close.png
Java8JiaochengHuizong/img/fullscreen.png
Java8JiaochengHuizong/img/loader.gif
Java8JiaochengHuizong/img/menu-icon.png
Java8JiaochengHuizong/img/save.png
Java8JiaochengHuizong/img/saved.png
Java8JiaochengHuizong/img/settings-s.png
Java8JiaochengHuizong/img/settings.png
Java8JiaochengHuizong/img/star.png
Java8JiaochengHuizong/js/__init__.py
Java8JiaochengHuizong/js/epub.js
Java8JiaochengHuizong/js/epub.min.js
Java8JiaochengHuizong/js/epub.min.map
Java8JiaochengHuizong/js/hooks.min.js
Java8JiaochengHuizong/js/hooks.min.map
Java8JiaochengHuizong/js/reader.js
Java8JiaochengHuizong/js/reader.js.map
Java8JiaochengHuizong/js/reader.min.js
Java8JiaochengHuizong/js/reader.min.map
Java8JiaochengHuizong/js/hooks/__init__.py
Java8JiaochengHuizong/js/hooks/extensions/__init__.py
Java8JiaochengHuizong/js/hooks/extensions/highlight.js
Java8JiaochengHuizong/js/libs/__init__.py
Java8JiaochengHuizong/js/libs/jquery.min.js
Java8JiaochengHuizong/js/libs/localforage.min.js
Java8JiaochengHuizong/js/libs/screenfull.js
Java8JiaochengHuizong/js/libs/screenfull.min.js
Java8JiaochengHuizong/js/libs/zip.min.js
Java8JiaochengHuizong/js/plugins/__init__.py
java_8_jiaocheng_huizong-2024.3.1.0.dist-info/METADATA
java_8_jiaocheng_huizong-2024.3.1.0.dist-info/WHEEL
java_8_jiaocheng_huizong-2024.3.1.0.dist-info/entry_points.txt
java_8_jiaocheng_huizong-2024.3.1.0.dist-info/top_level.txt
java_8_jiaocheng_huizong-2024.3.1.0.dist-info/RECORD
